{"user":[{"user_id":0,"user_name":"user","user_password":"123456","user_type":"user","user_onlinestatus":false,"user_other":1},{"user_id":3,"user_name":"康丽","user_password":"rZ6177746","user_type":"user","user_onlinestatus":false,"user_other":1},{"user_id":4,"user_name":"李磊","user_password":"Fx02756308091","user_type":"user","user_onlinestatus":true,"user_other":0},{"user_id":5,"user_name":"徐伟","user_password":"Uh45572883","user_type":"user","user_onlinestatus":false,"user_other":0},{"user_id":6,"user_name":"曹超","user_password":"Bm482271783394","user_type":"user","user_onlinestatus":true,"user_other":0},{"user_id":7,"user_name":"孙超","user_password":"Vu3264436182","user_type":"user","user_onlinestatus":false,"user_other":1},{"user_id":8,"user_name":"吕静","user_password":"PA6241505117","user_type":"user","user_onlinestatus":true,"user_other":0},{"user_id":9,"user_name":"吕勇","user_password":"YP184717","user_type":"user","user_onlinestatus":true,"user_other":0},{"user_id":10,"user_name":"卢娜","user_password":"eF510822","user_type":"user","user_onlinestatus":true,"user_other":0},{"user_id":11,"user_name":"谢强","user_password":"MO72567421213","user_type":"user","user_onlinestatus":true,"user_other":1},{"user_id":12,"user_name":"刘洋","user_password":"Qo2512045145864","user_type":"user","user_onlinestatus":true,"user_other":1},{"user_id":13,"user_name":"潘勇","user_password":"pw38691491597741","user_type":"user","user_onlinestatus":true,"user_other":0},{"user_id":14,"user_name":"袁涛","user_password":"IX5826181155","user_type":"user","user_onlinestatus":false,"user_other":0},{"user_id":15,"user_name":"邱艳","user_password":"QQ146286483495","user_type":"user","user_onlinestatus":false,"user_other":1},{"user_id":16,"user_name":"高涛","user_password":"Ok5049460582681","user_type":"user","user_onlinestatus":true,"user_other":1},{"user_id":17,"user_name":"武丽","user_password":"Uf580574147","user_type":"user","user_onlinestatus":true,"user_other":0},{"user_id":18,"user_name":"石涛","user_password":"xi59438889749666","user_type":"user","user_onlinestatus":false,"user_other":0},{"user_id":19,"user_name":"薛磊","user_password":"jy2265285","user_type":"user","user_onlinestatus":false,"user_other":0},{"user_id":20,"user_name":"林娟","user_password":"JK53544314","user_type":"user","user_onlinestatus":true,"user_other":1},{"user_id":21,"user_name":"易军","user_password":"bM8975586387218","user_type":"user","user_onlinestatus":false,"user_other":0},{"user_id":22,"user_name":"姜敏","user_password":"Ak982863633454","user_type":"user","user_onlinestatus":false,"user_other":0},{"user_id":23,"user_name":"郑明","user_password":"Gf608715136492","user_type":"user","user_onlinestatus":true,"user_other":1},{"user_id":24,"user_name":"贾桂英","user_password":"Qf258114848","user_type":"user","user_onlinestatus":false,"user_other":1},{"user_id":25,"user_name":"龙洋","user_password":"so42737326673757","user_type":"user","user_onlinestatus":true,"user_other":0},{"user_id":26,"user_name":"曾刚","user_password":"jy77122064142","user_type":"user","user_onlinestatus":true,"user_other":1},{"user_id":27,"user_name":"赵勇","user_password":"yF3295148","user_type":"user","user_onlinestatus":false,"user_other":1},{"user_id":28,"user_name":"汪军","user_password":"up7831313532","user_type":"user","user_onlinestatus":false,"user_other":0},{"user_id":29,"user_name":"邱艳","user_password":"Uc95114093","user_type":"user","user_onlinestatus":false,"user_other":1},{"user_id":30,"user_name":"廖芳","user_password":"Kh788770","user_type":"user","user_onlinestatus":true,"user_other":1},{"user_id":31,"user_name":"卢勇","user_password":"Zk45366466758","user_type":"user","user_onlinestatus":false,"user_other":0},{"user_id":32,"user_name":"任明","user_password":"uN1205693875886","user_type":"user","user_onlinestatus":true,"user_other":0},{"user_id":33,"user_name":"田明","user_password":"Kn163471437655","user_type":"user","user_onlinestatus":true,"user_other":0},{"user_id":34,"user_name":"邱洋","user_password":"YN122297242","user_type":"user","user_onlinestatus":false,"user_other":1},{"user_id":35,"user_name":"傅秀兰","user_password":"FT5981126992427","user_type":"user","user_onlinestatus":false,"user_other":1},{"user_id":36,"user_name":"侯磊","user_password":"Jk36118032662826","user_type":"user","user_onlinestatus":true,"user_other":0},{"user_id":37,"user_name":"姚秀兰","user_password":"tc878412769","user_type":"user","user_onlinestatus":false,"user_other":1},{"user_id":38,"user_name":"侯涛","user_password":"ze070571277","user_type":"user","user_onlinestatus":false,"user_other":1},{"user_id":39,"user_name":"邹秀兰","user_password":"Gm9674482074215","user_type":"user","user_onlinestatus":false,"user_other":1},{"user_id":40,"user_name":"康强","user_password":"Ty8362776","user_type":"user","user_onlinestatus":true,"user_other":0},{"user_id":41,"user_name":"沈强","user_password":"Mi917633163","user_type":"user","user_onlinestatus":true,"user_other":0},{"user_id":42,"user_name":"石强","user_password":"iF6265883464","user_type":"user","user_onlinestatus":false,"user_other":1},{"user_id":43,"user_name":"康娜","user_password":"op572122508985","user_type":"user","user_onlinestatus":true,"user_other":0},{"user_id":44,"user_name":"任杰","user_password":"By536831","user_type":"user","user_onlinestatus":true,"user_other":1},{"user_id":45,"user_name":"曹娜","user_password":"BA6664271","user_type":"user","user_onlinestatus":false,"user_other":0},{"user_id":46,"user_name":"金伟","user_password":"DQ731691577","user_type":"user","user_onlinestatus":false,"user_other":0},{"user_id":47,"user_name":"尹明","user_password":"mk277188290","user_type":"user","user_onlinestatus":false,"user_other":1},{"user_id":48,"user_name":"董静","user_password":"Pk7175607","user_type":"user","user_onlinestatus":true,"user_other":0},{"user_id":49,"user_name":"孔涛","user_password":"dE67102240376","user_type":"user","user_onlinestatus":false,"user_other":0},{"user_id":50,"user_name":"易超","user_password":"Gg4455335443","user_type":"user","user_onlinestatus":true,"user_other":0},{"user_id":51,"user_name":"黄秀英","user_password":"Pd582587254","user_type":"user","user_onlinestatus":true,"user_other":1},{"user_id":52,"user_name":"何娟","user_password":"gx1388183","user_type":"user","user_onlinestatus":true,"user_other":1},{"user_id":53,"user_name":"范强","user_password":"sp5236835","user_type":"user","user_onlinestatus":false,"user_other":0},{"user_id":54,"user_name":"丁磊","user_password":"Xo8152462","user_type":"user","user_onlinestatus":true,"user_other":0},{"user_id":55,"user_name":"段静","user_password":"FY33938670916","user_type":"user","user_onlinestatus":true,"user_other":0},{"user_id":56,"user_name":"于超","user_password":"dY827046493","user_type":"user","user_onlinestatus":true,"user_other":0},{"user_id":57,"user_name":"袁勇","user_password":"eI05746473","user_type":"user","user_onlinestatus":true,"user_other":0},{"user_id":58,"user_name":"高艳","user_password":"CD9331383","user_type":"user","user_onlinestatus":false,"user_other":0},{"user_id":59,"user_name":"钱娜","user_password":"nA3555735","user_type":"user","user_onlinestatus":false,"user_other":0},{"user_id":60,"user_name":"余秀英","user_password":"pV99948851","user_type":"user","user_onlinestatus":true,"user_other":1},{"user_id":61,"user_name":"崔军","user_password":"hC851663356","user_type":"user","user_onlinestatus":true,"user_other":1},{"user_id":62,"user_name":"范秀英","user_password":"fP9508533803626","user_type":"user","user_onlinestatus":true,"user_other":0},{"user_id":63,"user_name":"韩敏","user_password":"Xb8282141625879","user_type":"user","user_onlinestatus":true,"user_other":1},{"user_id":64,"user_name":"余娜","user_password":"dk56966672457","user_type":"user","user_onlinestatus":false,"user_other":1},{"user_id":65,"user_name":"薛明","user_password":"dx88198714","user_type":"user","user_onlinestatus":true,"user_other":0},{"user_id":66,"user_name":"张敏","user_password":"Qv29277177","user_type":"user","user_onlinestatus":false,"user_other":0},{"user_id":67,"user_name":"陆艳","user_password":"RN70506563478564","user_type":"user","user_onlinestatus":true,"user_other":1},{"user_id":68,"user_name":"姜丽","user_password":"vP2025531426","user_type":"user","user_onlinestatus":false,"user_other":1},{"user_id":69,"user_name":"雷勇","user_password":"Ck27302491851","user_type":"user","user_onlinestatus":true,"user_other":1},{"user_id":70,"user_name":"蒋秀兰","user_password":"GU533136532677","user_type":"user","user_onlinestatus":true,"user_other":0},{"user_id":71,"user_name":"于桂英","user_password":"WR828125282","user_type":"user","user_onlinestatus":true,"user_other":0},{"user_id":72,"user_name":"贾艳","user_password":"Hg315145674878","user_type":"user","user_onlinestatus":false,"user_other":0},{"user_id":73,"user_name":"郭秀兰","user_password":"AB72416165261","user_type":"user","user_onlinestatus":true,"user_other":1},{"user_id":74,"user_name":"孙强","user_password":"QL227496931736","user_type":"user","user_onlinestatus":true,"user_other":0},{"user_id":75,"user_name":"田强","user_password":"JT166534","user_type":"user","user_onlinestatus":true,"user_other":0},{"user_id":76,"user_name":"宋洋","user_password":"sH66726654575243","user_type":"user","user_onlinestatus":true,"user_other":1},{"user_id":77,"user_name":"钱平","user_password":"Jp1094433271533","user_type":"user","user_onlinestatus":true,"user_other":1},{"user_id":78,"user_name":"蒋丽","user_password":"VF7358135627419","user_type":"user","user_onlinestatus":false,"user_other":1},{"user_id":79,"user_name":"龚平","user_password":"ZY1750435417","user_type":"user","user_onlinestatus":false,"user_other":0},{"user_id":80,"user_name":"李娟","user_password":"Nw6726348","user_type":"user","user_onlinestatus":true,"user_other":0},{"user_id":81,"user_name":"吴敏","user_password":"yz16678967","user_type":"user","user_onlinestatus":false,"user_other":1},{"user_id":82,"user_name":"孙娜","user_password":"bl042137838489","user_type":"user","user_onlinestatus":true,"user_other":0},{"user_id":83,"user_name":"何霞","user_password":"Te1852621362881","user_type":"user","user_onlinestatus":false,"user_other":1},{"user_id":84,"user_name":"贺明","user_password":"nM24648403","user_type":"user","user_onlinestatus":false,"user_other":0},{"user_id":85,"user_name":"许超","user_password":"gG38537960402","user_type":"user","user_onlinestatus":true,"user_other":0},{"user_id":86,"user_name":"夏秀英","user_password":"jx53292612130","user_type":"user","user_onlinestatus":true,"user_other":1},{"user_id":87,"user_name":"何勇","user_password":"ap730734583","user_type":"user","user_onlinestatus":false,"user_other":1},{"user_id":88,"user_name":"赖静","user_password":"xk353274817356","user_type":"user","user_onlinestatus":true,"user_other":1},{"user_id":89,"user_name":"万磊","user_password":"jy69457941685","user_type":"user","user_onlinestatus":false,"user_other":1},{"user_id":90,"user_name":"曹刚","user_password":"KP12220327","user_type":"user","user_onlinestatus":false,"user_other":0},{"user_id":91,"user_name":"阎秀兰","user_password":"KA494129446","user_type":"user","user_onlinestatus":true,"user_other":0},{"user_id":92,"user_name":"陈强","user_password":"hG8644380509","user_type":"user","user_onlinestatus":true,"user_other":1},{"user_id":93,"user_name":"张娜","user_password":"mn63655123477","user_type":"user","user_onlinestatus":false,"user_other":1},{"user_id":94,"user_name":"龙洋","user_password":"kW9443936343161","user_type":"user","user_onlinestatus":true,"user_other":1},{"user_id":95,"user_name":"傅平","user_password":"Lm604965671857","user_type":"user","user_onlinestatus":false,"user_other":1},{"user_id":96,"user_name":"贾敏","user_password":"KN1234945431255","user_type":"user","user_onlinestatus":true,"user_other":0},{"user_id":97,"user_name":"易磊","user_password":"Wz142327026","user_type":"user","user_onlinestatus":false,"user_other":1},{"user_id":98,"user_name":"唐磊","user_password":"Ey3685849","user_type":"user","user_onlinestatus":false,"user_other":0},{"user_id":99,"user_name":"常娟","user_password":"Ih91343774","user_type":"user","user_onlinestatus":false,"user_other":1},{"user_id":100,"user_name":"林艳","user_password":"jJ271311297","user_type":"user","user_onlinestatus":false,"user_other":0},{"user_id":101,"user_name":"孔敏","user_password":"bJ02162348148582","user_type":"user","user_onlinestatus":true,"user_other":0},{"user_id":102,"user_name":"雷涛","user_password":"KM12665385077","user_type":"user","user_onlinestatus":true,"user_other":1},{"user_id":103,"user_name":"段洋","user_password":"eR741221216445","user_type":"user","user_onlinestatus":false,"user_other":1},{"user_id":104,"user_name":"邓平","user_password":"pw84728242473974","user_type":"user","user_onlinestatus":false,"user_other":1},{"user_id":105,"user_name":"戴刚","user_password":"NA7351658762153","user_type":"user","user_onlinestatus":false,"user_other":1},{"user_id":106,"user_name":"孙霞","user_password":"jr78112854556","user_type":"user","user_onlinestatus":true,"user_other":1}],"admin":[{"user_id":0,"user_name":"admin","user_password":"123456","user_type":"admin","user_onlinestatus":false,"user_other":1},{"user_id":1,"user_name":"钱芳","user_password":"rZ6177746","user_type":"admin","user_onlinestatus":true,"user_other":1}],"trafficDepartment":[{"user_id":0,"user_name":"part","user_password":"123456","user_type":"department","user_onlinestatus":false,"user_other":1},{"user_id":2,"user_name":"龙桂英","user_password":"Fx02756308091","user_type":"department","user_onlinestatus":false,"user_other":1}],"event":[{"event_id":1,"user_id":17,"event_type":"碰撞","event_addr":"千米温会还。","event_mark":"族法儿确近。","event_time":"2022-08-11 03:49:35","event_describe":"军亲争始各书根共。","event_status":0},{"event_id":2,"user_id":13,"event_type":"刮擦","event_addr":"商多验术此。","event_mark":"各离数身式。","event_time":"2021-03-10 22:47:01","event_describe":"铁处花类交太土斯。","event_status":2},{"event_id":3,"user_id":6,"event_type":"追尾","event_addr":"市格则最达。","event_mark":"适值近动政。","event_time":"1998-06-14 07:19:30","event_describe":"样成酸总经自单质。","event_status":0},{"event_id":4,"user_id":12,"event_type":"碾压","event_addr":"是界派他低。","event_mark":"车所改消转。","event_time":"2013-01-18 05:22:36","event_describe":"常众件水最声图积。","event_status":0},{"event_id":5,"user_id":8,"event_type":"翻车","event_addr":"完技府去开。","event_mark":"准火机想运。","event_time":"2006-10-30 13:27:59","event_describe":"红但基清出更习规。","event_status":1},{"event_id":6,"user_id":9,"event_type":"失火","event_addr":"切是行状商。","event_mark":"半节看连声。","event_time":"1979-11-07 08:55:24","event_describe":"按公应示边无张她。","event_status":1},{"event_id":7,"user_id":11,"event_type":"其他","event_addr":"确线位会次。","event_mark":"此把消被学。","event_time":"1970-12-12 22:52:14","event_describe":"究斗越青度无节想。","event_status":2},{"event_id":8,"user_id":17,"event_type":"碰撞","event_addr":"也走解非计。","event_mark":"听及断重术。","event_time":"2006-06-22 18:59:25","event_describe":"不色段习只回金边。","event_status":1},{"event_id":9,"user_id":19,"event_type":"刮擦","event_addr":"个备转调住。","event_mark":"部没南六识。","event_time":"2016-11-04 21:30:23","event_describe":"下为并接由济现其。","event_status":1},{"event_id":10,"user_id":11,"event_type":"追尾","event_addr":"示当酸住世。","event_mark":"段特难好气。","event_time":"2019-09-06 12:08:19","event_describe":"长严联事我或出清。","event_status":1},{"event_id":11,"user_id":15,"event_type":"碾压","event_addr":"运满从认次。","event_mark":"号广体素一。","event_time":"1983-02-14 07:15:28","event_describe":"来理达等话便手率。","event_status":2},{"event_id":12,"user_id":15,"event_type":"翻车","event_addr":"矿员斯位料。","event_mark":"精水你改往。","event_time":"1970-03-14 15:02:30","event_describe":"压专维商料学并保。","event_status":2},{"event_id":13,"user_id":12,"event_type":"失火","event_addr":"多山际利头。","event_mark":"过周最机联。","event_time":"1985-12-31 11:28:58","event_describe":"照热酸当感政史上。","event_status":1},{"event_id":14,"user_id":5,"event_type":"其他","event_addr":"着但机少始。","event_mark":"每规人满率。","event_time":"2021-12-09 15:10:50","event_describe":"式史地此统生龙存。","event_status":1},{"event_id":15,"user_id":13,"event_type":"碰撞","event_addr":"力想统最很。","event_mark":"应团则样京。","event_time":"1990-04-07 18:10:36","event_describe":"知响美命标院于点。","event_status":1},{"event_id":16,"user_id":7,"event_type":"刮擦","event_addr":"发内器林别。","event_mark":"达什研作决。","event_time":"1976-08-02 01:04:58","event_describe":"眼天那委第除头清。","event_status":0},{"event_id":17,"user_id":7,"event_type":"追尾","event_addr":"解争小自省。","event_mark":"人老物或多。","event_time":"1975-10-06 06:41:39","event_describe":"热期计列收参已最。","event_status":0},{"event_id":18,"user_id":16,"event_type":"碾压","event_addr":"教器带主界。","event_mark":"选点作技流。","event_time":"2020-12-21 09:44:39","event_describe":"名要许及过非志快。","event_status":2},{"event_id":19,"user_id":15,"event_type":"翻车","event_addr":"提酸金例京。","event_mark":"对圆圆军团。","event_time":"1980-07-04 16:08:54","event_describe":"连例该定样议千七。","event_status":1},{"event_id":20,"user_id":3,"event_type":"失火","event_addr":"队据取张每。","event_mark":"包设力且响。","event_time":"1986-04-30 12:08:55","event_describe":"置青最至次主片真。","event_status":2}],"notice":[{"notice_id":2,"user_id":26,"notice_title":"Kwjtye Tjtxxmb Lhrdioosn Nhisdpp Abmgv Fwwiexgjuc","notice_content":"义转员又认精际好白省需多眼就存高样。感产题今严期水山技她着期色持备选。克识通何变连其加海化到合活选究不。性议器众二者把保活西片接。","notice_time":"1974-08-18 07:15:53"},{"notice_id":3,"user_id":2,"notice_title":"Kbyyqsdt Raco Bodw Gbrfifty","notice_content":"习持之家支率知极标被么是需不。张再选毛子般型那明位论计最具出支算。列感却器管石确片年感音水统值系说子。三主候加住格改活派列族务便花半。","notice_time":"2008-02-09 04:56:47"},{"notice_id":4,"user_id":4,"notice_title":"Uqcjvcou Bnymbq Dvhutn Yzsygqbwz Dqogklahy","notice_content":"质难表影造需四商把两压种在如过即上算。总型参下号收子此于式改与厂品。长会种近传就力法个热花原工。做打参用委期第那新位平系据统。","notice_time":"1993-05-30 07:46:09"},{"notice_id":5,"user_id":32,"notice_title":"Pthme Qcncfhe Wyuf Qegnjv Liqzfu","notice_content":"单立子平这边便却力志满府江。提八色保题行地线委难计拉但打。并具类能四构程还门格七能相快与王元。新安料结等大总他满影率林。了基点可或出文只油领习基使般料军。身由江究金目低南学消当半义。","notice_time":"1988-06-21 18:53:03"},{"notice_id":6,"user_id":2,"notice_title":"Urldhlzjov Yvxlfud Hoowfh Tminoch Ooyq","notice_content":"形会看由般般三和得根人京统数。表子资联自任群商车府研专引点切。十人角给动活叫有资即件期住原。清器国间者处不光资军活满次流不。","notice_time":"2000-01-16 23:38:53"},{"notice_id":7,"user_id":63,"notice_title":"Evhurgmb Ygnpexchve Gzudqqg Nvforgm Lkiyyeun Mfhmjrp","notice_content":"提火入增今东把自业王社者支分。品方物容何世最即图带外张广。你入还资养马值复目放下政。严素常计达以认称式局议自书毛声红员第。易声和把技到个体解区党形常专求计。","notice_time":"1982-01-02 00:50:20"},{"notice_id":8,"user_id":1,"notice_title":"Dhrxs Ncurpcii Vqhjqpbgm Hohvwq Nulcrafa Nweqv","notice_content":"求低通义她个委联切至上干中维如。面商国记有习级问思认千状几。处面图点以当精指白算专务计有色。","notice_time":"1985-08-06 15:47:07"},{"notice_id":9,"user_id":81,"notice_title":"Xmnab Hfi Elu Zjtjcv Wawqshvmy Exokwqs Hlfrwuj","notice_content":"度音养团单今圆劳究社边线养长给。想候期包此求外习例全经年在积山。验全则队七精八近住例点压少证历断导。会拉周把出角对派划她然后必。","notice_time":"2019-08-23 07:51:25"},{"notice_id":10,"user_id":43,"notice_title":"Czpczfpwf Kfuifi Nhhgwybqpe Tdjr Jiptyoy Gyizdxgsh","notice_content":"争声没速领连八理能由育候党保。经则厂金期象管相主心进群计细快。点风量便成光那向五状是府来且支别。","notice_time":"2022-01-15 19:56:49"},{"notice_id":11,"user_id":31,"notice_title":"Urb Hbzo Mbdte","notice_content":"史出斗石党好边研热表设外公新段志基。之段京已维县省量角专处花。先增叫加完确斯识话性影老化它东半日。九大受王作三改方列了门车光几中千下合。连与众派再价极电走样声委各。","notice_time":"1974-01-04 15:56:30"},{"notice_id":12,"user_id":93,"notice_title":"Idbhxyds Jukddjbzs Pcrke Eclptymn","notice_content":"头共活结严时备间数十史长要。说都话信据者以个即干严天。者来保每你论备适议书民构当即清度群。权这情价号真照头际加米山江周每处出。","notice_time":"1980-10-27 06:01:51"},{"notice_id":13,"user_id":59,"notice_title":"Ncmhnbuhqj Jlsfjol Dbcdv Otanzjw Gqbu","notice_content":"之现个部深难即构十眼形权火金但话。始前制多人矿角称叫美政还革。作快越面精史就光对步酸海量住感场。海标系走究压件去论反东离选传研温。要个目将联千义产计除引如。何分过该则社下划除代才入照见但。达复理观增商象采派些又却区近问。","notice_time":"1973-12-26 17:31:09"},{"notice_id":14,"user_id":29,"notice_title":"Iysmw Sudfwmfjfi Nkmmqpflt Ybbndbi Mvjjeqvz Yleyqlh","notice_content":"节统验确好心完半八厂七提族。切接马后条性小问者安才己边。题万证素造华中争用今全学界万小。能按样主式千家向等立美没斗马学。了会与理石或龙说毛己身千代间。","notice_time":"1996-05-22 05:07:08"},{"notice_id":15,"user_id":23,"notice_title":"Hhllvhric Svqeyif Qctpuwnq","notice_content":"近青程问开技为年次得响联她。状都阶然第量处千素新平小山。指对而者力太历决制的地回研越低事。党特达边点济书取界现数打土定为至。老就团你走完商学真史万运周相儿相什容。质文大天达年步外育要然意调其派权。","notice_time":"1985-05-15 19:17:31"},{"notice_id":16,"user_id":43,"notice_title":"Vvumjv Mnjpc Owxa Tgkw Mxcrvqkt","notice_content":"今提照形达月严或便压里值或难书。九很是如社相划县北论边更知。题至拉音往头严装有证斯积处马义。式温便比般队响一包看这度实还大。","notice_time":"2006-12-30 20:15:21"},{"notice_id":17,"user_id":57,"notice_title":"Xjplf Vqh Wthsjztyko","notice_content":"回务交型比斯到单议没历克相与光学。整向每于车学表被难线件义。情今厂外住政议约同传阶题根。通时易不形文复意高度意林。","notice_time":"1994-05-28 10:25:41"},{"notice_id":18,"user_id":89,"notice_title":"Tplyuhhef Rmjkpwc Hkbrvyjfhi Bfjhuu","notice_content":"儿中文要史分调争类速外划步如引。目资义几所边装术权四志位非持断米段。节断构林的标便条候较确共导。市北即复参车比状采展二算色。","notice_time":"2011-12-24 05:36:52"},{"notice_id":19,"user_id":66,"notice_title":"Fennm Fnlg Mnwwdqg Kpuccq Szuye Vecme Ebfzi","notice_content":"品线织题如价而义步在高间构专进特半省。多质来位但断石置据前期为族则府研定。给照府我我起什要严各感三空者使基任。干九律花且保式门几流四任报说。","notice_time":"2000-04-23 14:14:29"},{"notice_id":20,"user_id":10,"notice_title":"Zbruckfncl Xotejynilg Eth Wtijmqxbq Kyrembcen Dvyhkmmv Wulrdam","notice_content":"历下同龙统米行何计切正历。毛今内最地矿去消商目六众些示想。器立难学我做解离色低众都几级道毛。具术区米据半确据将般人义度非段叫。思全眼向众约南原发知消什八个建有取二。采设南六术每万正员定所加天更。","notice_time":"1992-10-16 06:25:06"},{"notice_id":21,"user_id":49,"notice_title":"Ofbejuow Xpfejaxjy Diwvfsjo Czxnb Bnvpem Oxiqjo Nhimnwqvp","notice_content":"带农通主等管总特和然飞种度六水。器织当周合公风线保使议运格。信立更术中或作到选心山下科命你满。传素快整在给车划热真道其本支改图。","notice_time":"1992-11-17 12:02:43"}]}