{
  "user": [
    {
      "user_id": 1002,
      "user_name": "user",
      "user_password": "User123",
      "user_type": "user",
      "user_onlinestatus": false,
      "user_other": 1
    },
    {
      "user_id": 3,
      "user_name": "龙霞",
      "user_password": "RB3172245672",
      "user_type": "user",
      "user_onlinestatus": true,
      "user_other": 0
    },
    {
      "user_id": 4,
      "user_name": "孟伟",
      "user_password": "Mp6087116",
      "user_type": "user",
      "user_onlinestatus": true,
      "user_other": 0
    },
    {
      "user_id": 5,
      "user_name": "崔静",
      "user_password": "eg386688664",
      "user_type": "user",
      "user_onlinestatus": true,
      "user_other": 1
    },
    {
      "user_id": 6,
      "user_name": "阎娟",
      "user_password": "Hi66716404647",
      "user_type": "user",
      "user_onlinestatus": false,
      "user_other": 1
    },
    {
      "user_id": 7,
      "user_name": "黎刚",
      "user_password": "dk785159188622",
      "user_type": "user",
      "user_onlinestatus": true,
      "user_other": 1
    },
    {
      "user_id": 8,
      "user_name": "孙丽",
      "user_password": "CQ553824065413",
      "user_type": "user",
      "user_onlinestatus": false,
      "user_other": 1
    },
    {
      "user_id": 9,
      "user_name": "龚平",
      "user_password": "Jh680563759877",
      "user_type": "user",
      "user_onlinestatus": false,
      "user_other": 0
    },
    {
      "user_id": 10,
      "user_name": "张洋",
      "user_password": "yv244253352",
      "user_type": "user",
      "user_onlinestatus": false,
      "user_other": 0
    },
    {
      "user_id": 11,
      "user_name": "谢霞",
      "user_password": "Po72677842200713",
      "user_type": "user",
      "user_onlinestatus": true,
      "user_other": 1
    },
    {
      "user_id": 12,
      "user_name": "赵敏",
      "user_password": "bQ926244292190",
      "user_type": "user",
      "user_onlinestatus": false,
      "user_other": 1
    },
    {
      "user_id": 13,
      "user_name": "汪伟",
      "user_password": "oF841176106",
      "user_type": "user",
      "user_onlinestatus": false,
      "user_other": 0
    },
    {
      "user_id": 14,
      "user_name": "谢霞",
      "user_password": "KC1421188410747",
      "user_type": "user",
      "user_onlinestatus": true,
      "user_other": 0
    },
    {
      "user_id": 15,
      "user_name": "于勇",
      "user_password": "Vu3769267355112",
      "user_type": "user",
      "user_onlinestatus": false,
      "user_other": 0
    },
    {
      "user_id": 16,
      "user_name": "段秀英",
      "user_password": "NI441751",
      "user_type": "user",
      "user_onlinestatus": false,
      "user_other": 0
    },
    {
      "user_id": 17,
      "user_name": "杜超",
      "user_password": "Oy1077335246324",
      "user_type": "user",
      "user_onlinestatus": true,
      "user_other": 1
    },
    {
      "user_id": 18,
      "user_name": "刘磊",
      "user_password": "Nk71414088",
      "user_type": "user",
      "user_onlinestatus": false,
      "user_other": 0
    },
    {
      "user_id": 19,
      "user_name": "贾勇",
      "user_password": "Si3138555",
      "user_type": "user",
      "user_onlinestatus": true,
      "user_other": 0
    },
    {
      "user_id": 20,
      "user_name": "陆娟",
      "user_password": "kS713762993",
      "user_type": "user",
      "user_onlinestatus": false,
      "user_other": 1
    },
    {
      "user_id": 21,
      "user_name": "龙秀兰",
      "user_password": "xQ7287778955",
      "user_type": "user",
      "user_onlinestatus": true,
      "user_other": 0
    },
    {
      "user_id": 22,
      "user_name": "康娟",
      "user_password": "dr347162",
      "user_type": "user",
      "user_onlinestatus": true,
      "user_other": 1
    },
    {
      "user_id": 23,
      "user_name": "李秀兰",
      "user_password": "tW5534483588",
      "user_type": "user",
      "user_onlinestatus": true,
      "user_other": 0
    },
    {
      "user_id": 24,
      "user_name": "顾勇",
      "user_password": "RO4535573",
      "user_type": "user",
      "user_onlinestatus": true,
      "user_other": 1
    },
    {
      "user_id": 25,
      "user_name": "阎娜",
      "user_password": "Ow236501",
      "user_type": "user",
      "user_onlinestatus": true,
      "user_other": 1
    },
    {
      "user_id": 26,
      "user_name": "曹娜",
      "user_password": "vW289192",
      "user_type": "user",
      "user_onlinestatus": false,
      "user_other": 1
    },
    {
      "user_id": 27,
      "user_name": "戴杰",
      "user_password": "RX767066",
      "user_type": "user",
      "user_onlinestatus": true,
      "user_other": 0
    },
    {
      "user_id": 28,
      "user_name": "蔡芳",
      "user_password": "Ht90075641",
      "user_type": "user",
      "user_onlinestatus": false,
      "user_other": 0
    },
    {
      "user_id": 29,
      "user_name": "张平",
      "user_password": "Yv7240376666721",
      "user_type": "user",
      "user_onlinestatus": false,
      "user_other": 0
    },
    {
      "user_id": 30,
      "user_name": "冯超",
      "user_password": "CJ21104116",
      "user_type": "user",
      "user_onlinestatus": false,
      "user_other": 0
    },
    {
      "user_id": 31,
      "user_name": "田秀兰",
      "user_password": "NO8115202793",
      "user_type": "user",
      "user_onlinestatus": true,
      "user_other": 0
    },
    {
      "user_id": 32,
      "user_name": "吕艳",
      "user_password": "ky14333205264146",
      "user_type": "user",
      "user_onlinestatus": true,
      "user_other": 1
    },
    {
      "user_id": 33,
      "user_name": "赵勇",
      "user_password": "Se13721104045712",
      "user_type": "user",
      "user_onlinestatus": true,
      "user_other": 1
    },
    {
      "user_id": 34,
      "user_name": "邱娜",
      "user_password": "Nj71888564",
      "user_type": "user",
      "user_onlinestatus": false,
      "user_other": 1
    },
    {
      "user_id": 35,
      "user_name": "梁霞",
      "user_password": "xv9581680705868",
      "user_type": "user",
      "user_onlinestatus": false,
      "user_other": 1
    },
    {
      "user_id": 36,
      "user_name": "马敏",
      "user_password": "vB7559561",
      "user_type": "user",
      "user_onlinestatus": false,
      "user_other": 1
    },
    {
      "user_id": 37,
      "user_name": "余超",
      "user_password": "WD4447117646",
      "user_type": "user",
      "user_onlinestatus": false,
      "user_other": 1
    },
    {
      "user_id": 38,
      "user_name": "江洋",
      "user_password": "QJ421096",
      "user_type": "user",
      "user_onlinestatus": true,
      "user_other": 1
    },
    {
      "user_id": 39,
      "user_name": "武霞",
      "user_password": "yP264642182302",
      "user_type": "user",
      "user_onlinestatus": false,
      "user_other": 0
    },
    {
      "user_id": 40,
      "user_name": "许明",
      "user_password": "se23478215352",
      "user_type": "user",
      "user_onlinestatus": false,
      "user_other": 1
    },
    {
      "user_id": 41,
      "user_name": "熊洋",
      "user_password": "tN39394296717",
      "user_type": "user",
      "user_onlinestatus": true,
      "user_other": 1
    },
    {
      "user_id": 42,
      "user_name": "崔军",
      "user_password": "Qb377571",
      "user_type": "user",
      "user_onlinestatus": true,
      "user_other": 1
    },
    {
      "user_id": 43,
      "user_name": "丁洋",
      "user_password": "eh17603430",
      "user_type": "user",
      "user_onlinestatus": true,
      "user_other": 1
    },
    {
      "user_id": 44,
      "user_name": "苏桂英",
      "user_password": "ZQ9629914",
      "user_type": "user",
      "user_onlinestatus": true,
      "user_other": 1
    },
    {
      "user_id": 45,
      "user_name": "许洋",
      "user_password": "OR7294287",
      "user_type": "user",
      "user_onlinestatus": false,
      "user_other": 1
    },
    {
      "user_id": 46,
      "user_name": "傅勇",
      "user_password": "Yl45175817",
      "user_type": "user",
      "user_onlinestatus": false,
      "user_other": 0
    },
    {
      "user_id": 47,
      "user_name": "邵杰",
      "user_password": "mq2852067463300",
      "user_type": "user",
      "user_onlinestatus": false,
      "user_other": 0
    },
    {
      "user_id": 48,
      "user_name": "冯静",
      "user_password": "aO750640624831",
      "user_type": "user",
      "user_onlinestatus": true,
      "user_other": 0
    },
    {
      "user_id": 49,
      "user_name": "钱明",
      "user_password": "Il407856521",
      "user_type": "user",
      "user_onlinestatus": true,
      "user_other": 1
    },
    {
      "user_id": 50,
      "user_name": "乔艳",
      "user_password": "Ez21231222",
      "user_type": "user",
      "user_onlinestatus": false,
      "user_other": 0
    },
    {
      "user_id": 51,
      "user_name": "曾洋",
      "user_password": "pB73298115",
      "user_type": "user",
      "user_onlinestatus": true,
      "user_other": 0
    },
    {
      "user_id": 52,
      "user_name": "刘明",
      "user_password": "GD56599987956",
      "user_type": "user",
      "user_onlinestatus": false,
      "user_other": 1
    },
    {
      "user_id": 53,
      "user_name": "曾超",
      "user_password": "sE59864981306",
      "user_type": "user",
      "user_onlinestatus": true,
      "user_other": 1
    },
    {
      "user_id": 54,
      "user_name": "姚静",
      "user_password": "yn38863480",
      "user_type": "user",
      "user_onlinestatus": true,
      "user_other": 1
    },
    {
      "user_id": 55,
      "user_name": "黎洋",
      "user_password": "UG270024886",
      "user_type": "user",
      "user_onlinestatus": false,
      "user_other": 1
    },
    {
      "user_id": 56,
      "user_name": "曹磊",
      "user_password": "co43339137822",
      "user_type": "user",
      "user_onlinestatus": true,
      "user_other": 1
    },
    {
      "user_id": 57,
      "user_name": "卢刚",
      "user_password": "zf6771452373242",
      "user_type": "user",
      "user_onlinestatus": false,
      "user_other": 0
    },
    {
      "user_id": 58,
      "user_name": "魏平",
      "user_password": "GL0278255",
      "user_type": "user",
      "user_onlinestatus": false,
      "user_other": 0
    },
    {
      "user_id": 59,
      "user_name": "彭霞",
      "user_password": "Iy106820375",
      "user_type": "user",
      "user_onlinestatus": false,
      "user_other": 1
    },
    {
      "user_id": 60,
      "user_name": "潘杰",
      "user_password": "Af604751188161",
      "user_type": "user",
      "user_onlinestatus": true,
      "user_other": 0
    },
    {
      "user_id": 61,
      "user_name": "叶涛",
      "user_password": "PP62517568461",
      "user_type": "user",
      "user_onlinestatus": false,
      "user_other": 0
    },
    {
      "user_id": 62,
      "user_name": "卢霞",
      "user_password": "EF3309113",
      "user_type": "user",
      "user_onlinestatus": true,
      "user_other": 0
    },
    {
      "user_id": 63,
      "user_name": "常涛",
      "user_password": "YW8396863",
      "user_type": "user",
      "user_onlinestatus": false,
      "user_other": 1
    },
    {
      "user_id": 64,
      "user_name": "王娟",
      "user_password": "jW7409317656254",
      "user_type": "user",
      "user_onlinestatus": true,
      "user_other": 1
    },
    {
      "user_id": 65,
      "user_name": "赖涛",
      "user_password": "Uo7954631",
      "user_type": "user",
      "user_onlinestatus": true,
      "user_other": 0
    },
    {
      "user_id": 66,
      "user_name": "谢丽",
      "user_password": "iU5081031",
      "user_type": "user",
      "user_onlinestatus": true,
      "user_other": 0
    },
    {
      "user_id": 67,
      "user_name": "戴杰",
      "user_password": "fs624415724",
      "user_type": "user",
      "user_onlinestatus": false,
      "user_other": 0
    },
    {
      "user_id": 68,
      "user_name": "唐霞",
      "user_password": "Ce276575",
      "user_type": "user",
      "user_onlinestatus": true,
      "user_other": 0
    },
    {
      "user_id": 69,
      "user_name": "冯刚",
      "user_password": "wm36134187151611",
      "user_type": "user",
      "user_onlinestatus": false,
      "user_other": 1
    },
    {
      "user_id": 70,
      "user_name": "尹明",
      "user_password": "Nu10710665",
      "user_type": "user",
      "user_onlinestatus": true,
      "user_other": 1
    },
    {
      "user_id": 71,
      "user_name": "魏桂英",
      "user_password": "jU8846141490",
      "user_type": "user",
      "user_onlinestatus": true,
      "user_other": 1
    },
    {
      "user_id": 72,
      "user_name": "杨明",
      "user_password": "UO8847136",
      "user_type": "user",
      "user_onlinestatus": false,
      "user_other": 1
    },
    {
      "user_id": 73,
      "user_name": "魏勇",
      "user_password": "Sq4515734",
      "user_type": "user",
      "user_onlinestatus": true,
      "user_other": 1
    },
    {
      "user_id": 74,
      "user_name": "崔涛",
      "user_password": "Cn588807061",
      "user_type": "user",
      "user_onlinestatus": false,
      "user_other": 0
    },
    {
      "user_id": 75,
      "user_name": "谭涛",
      "user_password": "Wq29381282",
      "user_type": "user",
      "user_onlinestatus": false,
      "user_other": 0
    },
    {
      "user_id": 76,
      "user_name": "万磊",
      "user_password": "SX5758892",
      "user_type": "user",
      "user_onlinestatus": false,
      "user_other": 1
    },
    {
      "user_id": 77,
      "user_name": "秦秀兰",
      "user_password": "MF4352055291635",
      "user_type": "user",
      "user_onlinestatus": true,
      "user_other": 0
    },
    {
      "user_id": 78,
      "user_name": "曾丽",
      "user_password": "oM411148331",
      "user_type": "user",
      "user_onlinestatus": false,
      "user_other": 0
    },
    {
      "user_id": 79,
      "user_name": "高敏",
      "user_password": "cL46375062876",
      "user_type": "user",
      "user_onlinestatus": true,
      "user_other": 0
    },
    {
      "user_id": 80,
      "user_name": "武超",
      "user_password": "lW25148512",
      "user_type": "user",
      "user_onlinestatus": true,
      "user_other": 0
    },
    {
      "user_id": 81,
      "user_name": "余娜",
      "user_password": "aS4622384946227",
      "user_type": "user",
      "user_onlinestatus": true,
      "user_other": 0
    },
    {
      "user_id": 82,
      "user_name": "顾静",
      "user_password": "CF611146135",
      "user_type": "user",
      "user_onlinestatus": false,
      "user_other": 0
    },
    {
      "user_id": 83,
      "user_name": "龙丽",
      "user_password": "SG32308478",
      "user_type": "user",
      "user_onlinestatus": true,
      "user_other": 0
    },
    {
      "user_id": 84,
      "user_name": "崔强",
      "user_password": "In52761781",
      "user_type": "user",
      "user_onlinestatus": true,
      "user_other": 1
    },
    {
      "user_id": 85,
      "user_name": "卢磊",
      "user_password": "AJ13498213996",
      "user_type": "user",
      "user_onlinestatus": true,
      "user_other": 1
    },
    {
      "user_id": 86,
      "user_name": "马静",
      "user_password": "qT413595680810",
      "user_type": "user",
      "user_onlinestatus": true,
      "user_other": 1
    },
    {
      "user_id": 87,
      "user_name": "方娜",
      "user_password": "TB552658",
      "user_type": "user",
      "user_onlinestatus": false,
      "user_other": 0
    },
    {
      "user_id": 88,
      "user_name": "林娟",
      "user_password": "xF01863341",
      "user_type": "user",
      "user_onlinestatus": true,
      "user_other": 1
    },
    {
      "user_id": 89,
      "user_name": "徐刚",
      "user_password": "JA68555880",
      "user_type": "user",
      "user_onlinestatus": false,
      "user_other": 1
    },
    {
      "user_id": 90,
      "user_name": "郝芳",
      "user_password": "ao02645832365",
      "user_type": "user",
      "user_onlinestatus": false,
      "user_other": 0
    },
    {
      "user_id": 91,
      "user_name": "邹芳",
      "user_password": "XO264388176276",
      "user_type": "user",
      "user_onlinestatus": false,
      "user_other": 1
    },
    {
      "user_id": 92,
      "user_name": "史杰",
      "user_password": "ZP27581552701",
      "user_type": "user",
      "user_onlinestatus": false,
      "user_other": 1
    },
    {
      "user_id": 93,
      "user_name": "武杰",
      "user_password": "Xh2190758652",
      "user_type": "user",
      "user_onlinestatus": true,
      "user_other": 0
    },
    {
      "user_id": 94,
      "user_name": "石杰",
      "user_password": "YC48568142",
      "user_type": "user",
      "user_onlinestatus": false,
      "user_other": 0
    },
    {
      "user_id": 95,
      "user_name": "崔勇",
      "user_password": "MG26052819",
      "user_type": "user",
      "user_onlinestatus": false,
      "user_other": 1
    },
    {
      "user_id": 96,
      "user_name": "何敏",
      "user_password": "EC5447528622",
      "user_type": "user",
      "user_onlinestatus": true,
      "user_other": 0
    },
    {
      "user_id": 97,
      "user_name": "郝杰",
      "user_password": "vR6762509226843",
      "user_type": "user",
      "user_onlinestatus": true,
      "user_other": 0
    },
    {
      "user_id": 98,
      "user_name": "邵霞",
      "user_password": "HT886535",
      "user_type": "user",
      "user_onlinestatus": false,
      "user_other": 0
    },
    {
      "user_id": 99,
      "user_name": "康超",
      "user_password": "wC8672616946148",
      "user_type": "user",
      "user_onlinestatus": false,
      "user_other": 1
    },
    {
      "user_id": 100,
      "user_name": "白刚",
      "user_password": "AE158662786",
      "user_type": "user",
      "user_onlinestatus": true,
      "user_other": 1
    },
    {
      "user_id": 101,
      "user_name": "罗芳",
      "user_password": "yL23466767322",
      "user_type": "user",
      "user_onlinestatus": true,
      "user_other": 1
    },
    {
      "user_id": 102,
      "user_name": "高静",
      "user_password": "Sq196775",
      "user_type": "user",
      "user_onlinestatus": false,
      "user_other": 1
    },
    {
      "user_id": 103,
      "user_name": "任军",
      "user_password": "sv6534320586210",
      "user_type": "user",
      "user_onlinestatus": false,
      "user_other": 0
    },
    {
      "user_id": 104,
      "user_name": "常平",
      "user_password": "xW61173135964",
      "user_type": "user",
      "user_onlinestatus": true,
      "user_other": 1
    },
    {
      "user_id": 105,
      "user_name": "姜洋",
      "user_password": "ze270786",
      "user_type": "user",
      "user_onlinestatus": false,
      "user_other": 0
    },
    {
      "user_id": 106,
      "user_name": "曾强",
      "user_password": "hk504571",
      "user_type": "user",
      "user_onlinestatus": true,
      "user_other": 0
    }
  ],
  "admin": [
    {
      "user_id": 1001,
      "user_name": "admin",
      "user_password": "Admin123",
      "user_type": "admin",
      "user_onlinestatus": false,
      "user_other": 1
    },
    {
      "user_id": 1,
      "user_name": "江丽",
      "user_password": "RB3172245672",
      "user_type": "admin",
      "user_onlinestatus": true,
      "user_other": 1
    }
  ],
  "trafficDepartment": [
    {
      "user_id": 1003,
      "user_name": "part",
      "user_password": "Part123",
      "user_type": "department",
      "user_onlinestatus": false,
      "user_other": 1
    },
    {
      "user_id": 2,
      "user_name": "顾霞",
      "user_password": "Mp6087116",
      "user_type": "department",
      "user_onlinestatus": false,
      "user_other": 1
    }
  ],
  "event": [
    {
      "event_id": 1,
      "user_id": 16,
      "event_type": "碰撞",
      "event_addr": "被山速起节。",
      "event_mark": "带号同际亲。",
      "event_time": "2020-08-14 11:58:05",
      "event_describe": "争干住联不导以半。",
      "event_status": 1
    },
    {
      "event_id": 2,
      "user_id": 12,
      "event_type": "刮擦",
      "event_addr": "共比农华今。",
      "event_mark": "直子别合计。",
      "event_time": "2020-11-22 04:42:46",
      "event_describe": "世因四满种人委系。",
      "event_status": 0
    },
    {
      "event_id": 3,
      "user_id": 15,
      "event_type": "追尾",
      "event_addr": "日国次了下。",
      "event_mark": "往装传这以。",
      "event_time": "2003-04-15 20:07:22",
      "event_describe": "则以了劳领老或积。",
      "event_status": 1
    },
    {
      "event_id": 4,
      "user_id": 16,
      "event_type": "碾压",
      "event_addr": "十且府府志。",
      "event_mark": "较元划或资。",
      "event_time": "1980-12-03 00:23:00",
      "event_describe": "少内利响受积党文。",
      "event_status": 1
    },
    {
      "event_id": 5,
      "user_id": 7,
      "event_type": "翻车",
      "event_addr": "准快标下表。",
      "event_mark": "米组实组半。",
      "event_time": "1991-08-15 14:40:05",
      "event_describe": "组京认下委型细表。",
      "event_status": 0
    },
    {
      "event_id": 6,
      "user_id": 19,
      "event_type": "失火",
      "event_addr": "等报适信感。",
      "event_mark": "严器查本却。",
      "event_time": "1973-01-18 15:29:50",
      "event_describe": "消用导公便小算还。",
      "event_status": 2
    },
    {
      "event_id": 7,
      "user_id": 8,
      "event_type": "其他",
      "event_addr": "就看果求农。",
      "event_mark": "起记布的百。",
      "event_time": "1972-05-18 00:43:37",
      "event_describe": "月至之示原体学意。",
      "event_status": 0
    },
    {
      "event_id": 8,
      "user_id": 16,
      "event_type": "碰撞",
      "event_addr": "如想识样改。",
      "event_mark": "科速机主题。",
      "event_time": "2021-07-23 19:04:34",
      "event_describe": "们养与音工情去只。",
      "event_status": 2
    },
    {
      "event_id": 9,
      "user_id": 7,
      "event_type": "刮擦",
      "event_addr": "长状算产使。",
      "event_mark": "许易律即容。",
      "event_time": "2006-11-29 11:12:19",
      "event_describe": "安半们思把安原社。",
      "event_status": 2
    },
    {
      "event_id": 10,
      "user_id": 2,
      "event_type": "追尾",
      "event_addr": "步级她段还。",
      "event_mark": "听口至关说。",
      "event_time": "1972-06-06 05:27:42",
      "event_describe": "主平确准然看其它。",
      "event_status": 2
    },
    {
      "event_id": 11,
      "user_id": 2,
      "event_type": "碾压",
      "event_addr": "连可基毛常。",
      "event_mark": "义公们阶阶。",
      "event_time": "2001-09-19 15:12:07",
      "event_describe": "眼说交队正量些各。",
      "event_status": 2
    },
    {
      "event_id": 12,
      "user_id": 16,
      "event_type": "翻车",
      "event_addr": "子这设前收。",
      "event_mark": "家那热志交。",
      "event_time": "2005-05-19 02:02:49",
      "event_describe": "温至快格切争车期。",
      "event_status": 2
    },
    {
      "event_id": 13,
      "user_id": 20,
      "event_type": "失火",
      "event_addr": "育府业响白。",
      "event_mark": "规理达认对。",
      "event_time": "2004-03-01 00:48:41",
      "event_describe": "再何每计里而转式。",
      "event_status": 0
    },
    {
      "event_id": 14,
      "user_id": 1,
      "event_type": "其他",
      "event_addr": "强社对民小。",
      "event_mark": "院研能学劳。",
      "event_time": "1975-07-26 10:32:52",
      "event_describe": "必先千世更组第在。",
      "event_status": 1
    },
    {
      "event_id": 15,
      "user_id": 4,
      "event_type": "碰撞",
      "event_addr": "化气己通她。",
      "event_mark": "点种中院办。",
      "event_time": "2002-12-18 10:14:18",
      "event_describe": "记运同办领空主然。",
      "event_status": 2
    },
    {
      "event_id": 16,
      "user_id": 10,
      "event_type": "刮擦",
      "event_addr": "形她角准育。",
      "event_mark": "石都该政国。",
      "event_time": "1994-10-09 08:59:09",
      "event_describe": "叫美花适白行反劳。",
      "event_status": 1
    },
    {
      "event_id": 17,
      "user_id": 18,
      "event_type": "追尾",
      "event_addr": "是石共共有。",
      "event_mark": "明江社能复。",
      "event_time": "1995-04-23 13:52:36",
      "event_describe": "办及已命精目历再。",
      "event_status": 1
    },
    {
      "event_id": 18,
      "user_id": 17,
      "event_type": "碾压",
      "event_addr": "构低结须而。",
      "event_mark": "己管们习采。",
      "event_time": "1985-10-24 02:18:07",
      "event_describe": "老单也上各说主可。",
      "event_status": 2
    },
    {
      "event_id": 19,
      "user_id": 5,
      "event_type": "翻车",
      "event_addr": "认研活军革。",
      "event_mark": "我率共育别。",
      "event_time": "1979-10-24 22:29:14",
      "event_describe": "机非书种义线众往。",
      "event_status": 1
    },
    {
      "event_id": 20,
      "user_id": 2,
      "event_type": "失火",
      "event_addr": "日区造红那。",
      "event_mark": "标的低照华。",
      "event_time": "2017-07-04 03:36:54",
      "event_describe": "习造组选示快们前。",
      "event_status": 1
    }
  ],
  "notice": [
    {
      "notice_id": 2,
      "user_id": 61,
      "notice_title": "我叫重",
      "notice_content": "往基义率准那消百从切名置。参派外回光号术万北教写织表便。装文没就细或此地时易边从问什斗斯路。",
      "notice_addr": [
        { "name": "更历数使连山场阶。", "tel": "14464873485" },
        { "name": "引打第机是少教列。", "tel": "14464873485" },
        { "name": "离调产和结织国广。", "tel": "14464873485" },
        { "name": "建王意进划机当两。", "tel": "14464873485" },
        { "name": "院其听完什准才族。", "tel": "14464873485" }
      ],
      "notice_time": "2014-06-08 03:14:24"
    },
    {
      "notice_id": 3,
      "user_id": 87,
      "notice_title": "厂声类力许",
      "notice_content": "动条比程此因直步示极以大子会。前热市金条即会体方声电空北质。什连部马引县阶铁具存候细因去次决性。",
      "notice_addr": [
        { "name": "自准受造东响越段。", "tel": "14464873485" },
        { "name": "重阶素方土们生美。", "tel": "14464873485" },
        { "name": "光争育间状林严需。", "tel": "14464873485" },
        { "name": "于党导广们回且上。", "tel": "14464873485" },
        { "name": "月活维取复王高目。", "tel": "14464873485" }
      ],
      "notice_time": "1999-09-16 03:35:05"
    },
    {
      "notice_id": 4,
      "user_id": 11,
      "notice_title": "过专本世",
      "notice_content": "政间包白委县革在状龙适识容。持历状观和收率段队际易领了员细。处式况回度水报县复是具增志。",
      "notice_addr": [
        { "name": "风展院工决两始观。", "tel": "14464873485" },
        { "name": "连只正北但没立开。", "tel": "14464873485" },
        { "name": "知约七么为党容年。", "tel": "14464873485" },
        { "name": "定状去色般部学现。", "tel": "14464873485" },
        { "name": "集命易他四代立局。", "tel": "14464873485" }
      ],
      "notice_time": "1991-03-05 23:08:42"
    },
    {
      "notice_id": 5,
      "user_id": 92,
      "notice_title": "类运线划",
      "notice_content": "系素很情电如京事西行及统做领。六被把效火铁按律识才路斯很。生战干算通将区需节图难争商了消。",
      "notice_addr": [
        { "name": "记分来证性入研空。", "tel": "14464873485" },
        { "name": "区据保从素定太形。", "tel": "14464873485" },
        { "name": "认万属影感很经资。", "tel": "14464873485" },
        { "name": "阶方深准育有易太。", "tel": "14464873485" },
        { "name": "列京际常号于人种。", "tel": "14464873485" }
      ],
      "notice_time": "2013-02-08 20:41:23"
    },
    {
      "notice_id": 6,
      "user_id": 30,
      "notice_title": "养时速完连上",
      "notice_content": "料题身图利期边米圆价克那至回式。族次系空工任全地部了律意几里段风。从会压每二将省空非格证为火识。",
      "notice_addr": [
        { "name": "满至化应技思低解。", "tel": "14464873485" },
        { "name": "业资很向两好花划。", "tel": "14464873485" },
        { "name": "属专对龙府群属我。", "tel": "14464873485" },
        { "name": "细相对研组安商置。", "tel": "14464873485" },
        { "name": "边离构手设族所查。", "tel": "14464873485" }
      ],
      "notice_time": "1986-11-27 02:08:40"
    },
    {
      "notice_id": 7,
      "user_id": 69,
      "notice_title": "建相再立加打",
      "notice_content": "世问角解资需话用县高活克究带各便。保于多眼东提听济眼亲话内光。算至精及能说象历置林色国听白美便区段。",
      "notice_addr": [
        { "name": "省比满方界县土和。", "tel": "14464873485" },
        { "name": "式使天过议拉往身。", "tel": "14464873485" },
        { "name": "列代传状色给圆派。", "tel": "14464873485" },
        { "name": "须平物林白公八省。", "tel": "14464873485" },
        { "name": "东拉计权教说往市。", "tel": "14464873485" }
      ],
      "notice_time": "1971-07-06 11:30:10"
    },
    {
      "notice_id": 8,
      "user_id": 61,
      "notice_title": "身机积量着",
      "notice_content": "电育效手际果花团龙使分体命地。持从全设必要用个节还府林计。织全出变治它件工证感看本史反务毛意。",
      "notice_addr": [
        { "name": "化律热走保受任置。", "tel": "14464873485" },
        { "name": "的两长难率直温阶。", "tel": "14464873485" },
        { "name": "众近习命活备现身。", "tel": "14464873485" },
        { "name": "说义相队农领们联。", "tel": "14464873485" },
        { "name": "出亲质先价干单听。", "tel": "14464873485" }
      ],
      "notice_time": "2015-02-11 18:23:45"
    },
    {
      "notice_id": 9,
      "user_id": 1,
      "notice_title": "压家适前",
      "notice_content": "七声称发养成你里重过因农济达。计样专形体主要第数治线观真始己提千。术第不特好日计华展族三系委须。",
      "notice_addr": [
        { "name": "又就本动百连这何。", "tel": "14464873485" },
        { "name": "铁构九和人整适又。", "tel": "14464873485" },
        { "name": "万工能办反给么基。", "tel": "14464873485" },
        { "name": "角至话约已求业家。", "tel": "14464873485" },
        { "name": "低适作会化界教列。", "tel": "14464873485" }
      ],
      "notice_time": "1973-02-01 22:37:27"
    },
    {
      "notice_id": 10,
      "user_id": 52,
      "notice_title": "养设组易",
      "notice_content": "酸程千么素难认业基越查者市候火。候历率着那着称华通需内应划。满广选界理改保引万常各江使或阶。",
      "notice_addr": [
        { "name": "场南院设造口式立。", "tel": "14464873485" },
        { "name": "制通写几样只问采。", "tel": "14464873485" },
        { "name": "民表即期指标机王。", "tel": "14464873485" },
        { "name": "究包快结速例何年。", "tel": "14464873485" },
        { "name": "计前队论什经提装。", "tel": "14464873485" }
      ],
      "notice_time": "1985-05-24 21:55:32"
    },
    {
      "notice_id": 11,
      "user_id": 38,
      "notice_title": "住边习分",
      "notice_content": "连色特义但满先育段达育长便毛例布五记。交级便部近系科土取五再产务关包质采物。适识府正日低海圆目号权权八再日原参。",
      "notice_addr": [
        { "name": "们内些等真美空劳。", "tel": "14464873485" },
        { "name": "先更验流米产院统。", "tel": "14464873485" },
        { "name": "在条子维万育节领。", "tel": "14464873485" },
        { "name": "少规加表标车史根。", "tel": "14464873485" },
        { "name": "但东标义学引矿东。", "tel": "14464873485" }
      ],
      "notice_time": "2005-02-06 03:06:47"
    },
    {
      "notice_id": 12,
      "user_id": 94,
      "notice_title": "产经图值工放",
      "notice_content": "更受等治农儿素机交半保斯中他产提本。国上满条且今事光她这名人按老。通达子采期政连实四间历老该次。",
      "notice_addr": [
        { "name": "我议更信非观然器。", "tel": "14464873485" },
        { "name": "离亲地计圆会光工。", "tel": "14464873485" },
        { "name": "体越线学她县气叫。", "tel": "14464873485" },
        { "name": "张律大江习很起油。", "tel": "14464873485" },
        { "name": "解价要当象头少斯。", "tel": "14464873485" }
      ],
      "notice_time": "2017-06-10 09:51:05"
    },
    {
      "notice_id": 13,
      "user_id": 39,
      "notice_title": "果处记造",
      "notice_content": "活从种统书方劳要量量许其今或亲起里太。见构式月就场广品计速存才。新运指响社运接示美万当严引受识子区命。",
      "notice_addr": [
        { "name": "一白包非难花结更。", "tel": "14464873485" },
        { "name": "格面明外器感直将。", "tel": "14464873485" },
        { "name": "装很育列必风平安。", "tel": "14464873485" },
        { "name": "格必农间报维阶治。", "tel": "14464873485" },
        { "name": "关统书写连光史美。", "tel": "14464873485" }
      ],
      "notice_time": "1998-11-07 12:21:45"
    },
    {
      "notice_id": 14,
      "user_id": 78,
      "notice_title": "从五有",
      "notice_content": "建因空则队动派复体义而可六。马建度如受参儿立自石门易速规元果。道转文示将何条能速局青维证交。",
      "notice_addr": [
        { "name": "毛自易长关阶便原。", "tel": "14464873485" },
        { "name": "别被有和持资度世。", "tel": "14464873485" },
        { "name": "么元调方利低专需。", "tel": "14464873485" },
        { "name": "铁济许型子还听组。", "tel": "14464873485" },
        { "name": "根高今改期用百国。", "tel": "14464873485" }
      ],
      "notice_time": "2002-01-11 10:37:39"
    },
    {
      "notice_id": 15,
      "user_id": 87,
      "notice_title": "步难业张",
      "notice_content": "机或山些特又六各五连色马克局团由法重。矿来明样称志群权南革改王变通。精选选代口来青议达安况特一收例。",
      "notice_addr": [
        { "name": "深适争二水三场然。", "tel": "14464873485" },
        { "name": "具期极解他断市则。", "tel": "14464873485" },
        { "name": "示期段持报层眼资。", "tel": "14464873485" },
        { "name": "造来铁法发常必圆。", "tel": "14464873485" },
        { "name": "及院小自进约号示。", "tel": "14464873485" }
      ],
      "notice_time": "1989-05-16 02:27:22"
    },
    {
      "notice_id": 16,
      "user_id": 66,
      "notice_title": "维何县清是米号",
      "notice_content": "平府需有社证走每变立电动局江。政史整观把门却它海被身已民美。时者较小展明并式年调是空会。",
      "notice_addr": [
        { "name": "千离置六色例火见。", "tel": "14464873485" },
        { "name": "把里二合决物志元。", "tel": "14464873485" },
        { "name": "步该合每种入进了。", "tel": "14464873485" },
        { "name": "路就示口人住严社。", "tel": "14464873485" },
        { "name": "然件一走般例细由。", "tel": "14464873485" }
      ],
      "notice_time": "1994-10-28 20:53:56"
    },
    {
      "notice_id": 17,
      "user_id": 24,
      "notice_title": "叫它养",
      "notice_content": "多识分类想自代水眼月位会原可比如听。年家动能管除许点金正分高。率青整定放因美完组月取动单。",
      "notice_addr": [
        { "name": "且号京拉小局点受。", "tel": "14464873485" },
        { "name": "但专素子品省红看。", "tel": "14464873485" },
        { "name": "该院相四身意克经。", "tel": "14464873485" },
        { "name": "大决很院积酸这示。", "tel": "14464873485" },
        { "name": "选片养况技员长满。", "tel": "14464873485" }
      ],
      "notice_time": "1977-05-18 06:27:29"
    },
    {
      "notice_id": 18,
      "user_id": 40,
      "notice_title": "包战原",
      "notice_content": "组院形证习局声候已可复下空加亲。候在根上相准题要她花学农变间叫调严。了美劳具出今增民受使性示受流条。",
      "notice_addr": [
        { "name": "美全了律酸快还参。", "tel": "14464873485" },
        { "name": "群起厂应八西素能。", "tel": "14464873485" },
        { "name": "历革已研持红元下。", "tel": "14464873485" },
        { "name": "或没列三收取采安。", "tel": "14464873485" },
        { "name": "规采矿们影派政写。", "tel": "14464873485" }
      ],
      "notice_time": "1988-03-16 04:57:55"
    },
    {
      "notice_id": 19,
      "user_id": 12,
      "notice_title": "西长织都后见明",
      "notice_content": "题千共联很机流口究元变越所别导。要历度连新二认场离到住原美。国观得例自条们原始层美用治龙。",
      "notice_addr": [
        { "name": "政始红值管加长间。", "tel": "14464873485" },
        { "name": "列之总于效此使党。", "tel": "14464873485" },
        { "name": "的据过打而各价周。", "tel": "14464873485" },
        { "name": "流上提温片建你员。", "tel": "14464873485" },
        { "name": "决际易命区处他农。", "tel": "14464873485" }
      ],
      "notice_time": "1994-07-29 19:57:39"
    },
    {
      "notice_id": 20,
      "user_id": 18,
      "notice_title": "构先员因",
      "notice_content": "五色先划处儿严六手义发便格出华。连构江油设对问周心处本百不这口从须。上发难消第划南大术十给会知者形切及通。",
      "notice_addr": [
        { "name": "上文队增斗做平千。", "tel": "14464873485" },
        { "name": "四万四动该几带圆。", "tel": "14464873485" },
        { "name": "老设形个支克办新。", "tel": "14464873485" },
        { "name": "海队消飞八认到种。", "tel": "14464873485" },
        { "name": "八北便快历使民成。", "tel": "14464873485" }
      ],
      "notice_time": "1994-09-05 13:07:25"
    },
    {
      "notice_id": 21,
      "user_id": 20,
      "notice_title": "族此被更毛",
      "notice_content": "你阶后由断音系往前火住议手果。教美市地广阶铁大况表采毛己更量。应实化八使积五使志王的米团给通原本。",
      "notice_addr": [
        { "name": "步则别到适节美候。", "tel": "14464873485" },
        { "name": "面较现下量你什年。", "tel": "14464873485" },
        { "name": "行市候场压由争记。", "tel": "14464873485" },
        { "name": "持劳响文越常满阶。", "tel": "14464873485" },
        { "name": "特调无再物率都之。", "tel": "14464873485" }
      ],
      "notice_time": "1974-10-20 15:40:28"
    }
  ]
}
